{
    "extension.description": "An Azure Virtual Machines extension for Visual Studio Code.",
    "azureVirtualMachines.refresh": "Refresh",
    "azureVirtualMachines.loadMore": "Load More",
    "azureVirtualMachines.createVirtualMachine": "Create Virtual Machine...",
    "azureVirtualMachines.openInPortal": "Open in Portal",
    "azureVirtualMachines.startVirtualMachine": "Start",
    "azureVirtualMachines.stopVirtualMachine": "Stop",
    "azureVirtualMachines.restartFunctionApp": "Restart",
    "azureVirtualMachines.deleteVirtualMachine": "Delete...",
    "azureVirtualMachines.addSshKey": "Add SSH Key...",
    "azureVirtualMachines.enableOutputTimestamps": "Prepends each line displayed in the output channel with a timestamp."
}
